{"userid":"user-id","deviceid":"d4e6b172e6e4600b","senseStartTime":"21:49:12:924 21 09 2017 -0700 PDT","senseStartTimeMillis":1506055752924,"dataType":"Battery","level":22,"scale":100,"temperature":349,"voltage":3755,"plugged":2,"status":"BATTERY_STATUS_CHARGING","health":"BATTERY_HEALTH_GOOD"}
{"userid":"user-id","deviceid":"d4e6b172e6e4600b","senseStartTime":"21:49:15:018 21 09 2017 -0700 PDT","senseStartTimeMillis":1506055755018,"dataType":"Battery","level":22,"scale":100,"temperature":350,"voltage":3758,"plugged":2,"status":"BATTERY_STATUS_CHARGING","health":"BATTERY_HEALTH_GOOD"}
{"userid":"user-id","deviceid":"d4e6b172e6e4600b","senseStartTime":"21:49:21:037 21 09 2017 -0700 PDT","senseStartTimeMillis":1506055761037,"dataType":"Battery","level":22,"scale":100,"temperature":350,"voltage":3769,"plugged":2,"status":"BATTERY_STATUS_CHARGING","health":"BATTERY_HEALTH_GOOD"}
{"userid":"user-id","deviceid":"d4e6b172e6e4600b","senseStartTime":"21:49:27:013 21 09 2017 -0700 PDT","senseStartTimeMillis":1506055767013,"dataType":"Battery","level":22,"scale":100,"temperature":350,"voltage":3771,"plugged":2,"status":"BATTERY_STATUS_CHARGING","health":"BATTERY_HEALTH_GOOD"}
{"userid":"user-id","deviceid":"d4e6b172e6e4600b","senseStartTime":"22:03:49:784 21 09 2017 -0700 PDT","senseStartTimeMillis":1506056629784,"dataType":"Battery","level":21,"scale":100,"temperature":362,"voltage":3647,"plugged":2,"status":"BATTERY_STATUS_CHARGING","health":"BATTERY_HEALTH_GOOD"}
{"userid":"user-id","deviceid":"d4e6b172e6e4600b","senseStartTime":"22:03:53:997 21 09 2017 -0700 PDT","senseStartTimeMillis":1506056633997,"dataType":"Battery","level":21,"scale":100,"temperature":364,"voltage":3652,"plugged":2,"status":"BATTERY_STATUS_CHARGING","health":"BATTERY_HEALTH_GOOD"}
{"userid":"user-id","deviceid":"d4e6b172e6e4600b","senseStartTime":"22:03:59:996 21 09 2017 -0700 PDT","senseStartTimeMillis":1506056639996,"dataType":"Battery","level":21,"scale":100,"temperature":365,"voltage":3637,"plugged":2,"status":"BATTERY_STATUS_CHARGING","health":"BATTERY_HEALTH_GOOD"}
{"userid":"user-id","deviceid":"d4e6b172e6e4600b","senseStartTime":"22:04:05:997 21 09 2017 -0700 PDT","senseStartTimeMillis":1506056645997,"dataType":"Battery","level":21,"scale":100,"temperature":366,"voltage":3724,"plugged":2,"status":"BATTERY_STATUS_CHARGING","health":"BATTERY_HEALTH_GOOD"}
{"userid":"user-id","deviceid":"d4e6b172e6e4600b","senseStartTime":"22:04:11:995 21 09 2017 -0700 PDT","senseStartTimeMillis":1506056651995,"dataType":"Battery","level":21,"scale":100,"temperature":367,"voltage":3674,"plugged":2,"status":"BATTERY_STATUS_CHARGING","health":"BATTERY_HEALTH_GOOD"}
{"userid":"user-id","deviceid":"d4e6b172e6e4600b","senseStartTime":"22:04:18:003 21 09 2017 -0700 PDT","senseStartTimeMillis":1506056658003,"dataType":"Battery","level":21,"scale":100,"temperature":368,"voltage":3740,"plugged":2,"status":"BATTERY_STATUS_CHARGING","health":"BATTERY_HEALTH_GOOD"}
{"userid":"user-id","deviceid":"d4e6b172e6e4600b","senseStartTime":"22:04:23:999 21 09 2017 -0700 PDT","senseStartTimeMillis":1506056663999,"dataType":"Battery","level":21,"scale":100,"temperature":368,"voltage":3744,"plugged":2,"status":"BATTERY_STATUS_CHARGING","health":"BATTERY_HEALTH_GOOD"}
{"userid":"user-id","deviceid":"d4e6b172e6e4600b","senseStartTime":"22:04:29:997 21 09 2017 -0700 PDT","senseStartTimeMillis":1506056669997,"dataType":"Battery","level":21,"scale":100,"temperature":368,"voltage":3745,"plugged":2,"status":"BATTERY_STATUS_CHARGING","health":"BATTERY_HEALTH_GOOD"}
{"userid":"user-id","deviceid":"d4e6b172e6e4600b","senseStartTime":"22:04:36:002 21 09 2017 -0700 PDT","senseStartTimeMillis":1506056676002,"dataType":"Battery","level":21,"scale":100,"temperature":369,"voltage":3749,"plugged":2,"status":"BATTERY_STATUS_CHARGING","health":"BATTERY_HEALTH_GOOD"}
{"userid":"user-id","deviceid":"d4e6b172e6e4600b","senseStartTime":"22:04:42:000 21 09 2017 -0700 PDT","senseStartTimeMillis":1506056682000,"dataType":"Battery","level":21,"scale":100,"temperature":369,"voltage":3746,"plugged":2,"status":"BATTERY_STATUS_CHARGING","health":"BATTERY_HEALTH_GOOD"}
{"userid":"user-id","deviceid":"d4e6b172e6e4600b","senseStartTime":"22:04:48:010 21 09 2017 -0700 PDT","senseStartTimeMillis":1506056688010,"dataType":"Battery","level":21,"scale":100,"temperature":368,"voltage":3752,"plugged":2,"status":"BATTERY_STATUS_CHARGING","health":"BATTERY_HEALTH_GOOD"}
{"userid":"user-id","deviceid":"d4e6b172e6e4600b","senseStartTime":"22:04:53:999 21 09 2017 -0700 PDT","senseStartTimeMillis":1506056693999,"dataType":"Battery","level":21,"scale":100,"temperature":368,"voltage":3753,"plugged":2,"status":"BATTERY_STATUS_CHARGING","health":"BATTERY_HEALTH_GOOD"}
{"userid":"user-id","deviceid":"d4e6b172e6e4600b","senseStartTime":"22:04:59:999 21 09 2017 -0700 PDT","senseStartTimeMillis":1506056699999,"dataType":"Battery","level":21,"scale":100,"temperature":368,"voltage":3754,"plugged":2,"status":"BATTERY_STATUS_CHARGING","health":"BATTERY_HEALTH_GOOD"}
